scx/__init__.py
scx/database.py
scx/optimize.py
scx/statistics.py
scx/utils.py
scx-1.3.0.dist-info/licenses/LICENSE
scx-1.3.0.dist-info/METADATA
scx-1.3.0.dist-info/WHEEL
scx-1.3.0.dist-info/top_level.txt
scx-1.3.0.dist-info/RECORD
