Metadata-Version: 2.4
Name: scx
Version: 1.3.0
Summary: MIT Supply Chain Python Package
Author-email: Connor Makowski <conmak@mit.edu>
Project-URL: Homepage, https://github.com/connor-makowski/scx
Project-URL: Bug Tracker, https://github.com/connor-makowski/scx/issues
Project-URL: Documentation, https://connor-makowski.github.io/scx/scx.html
Classifier: Programming Language :: Python :: 3
Classifier: License :: OSI Approved :: MIT License
Classifier: Operating System :: OS Independent
Requires-Python: >=3.11
License-File: LICENSE
Requires-Dist: type_enforced<3.0.0,>=2.2.3
Requires-Dist: PuLP==3.3.0
Requires-Dist: duckdb==1.4.0
Dynamic: license-file
